fyoo/__init__.py
fyoo/__main__.py
fyoo/cli.py
fyoo/exception.py
fyoo/parser.py
fyoo/template/__init__.py
fyoo/template/attributes.py
fyoo/template/filters.py
fyoo-1.1.0.dist-info/LICENSE
fyoo-1.1.0.dist-info/METADATA
fyoo-1.1.0.dist-info/WHEEL
fyoo-1.1.0.dist-info/entry_points.txt
fyoo-1.1.0.dist-info/top_level.txt
fyoo-1.1.0.dist-info/RECORD
