Metadata-Version: 2.1
Name: fyoo
Version: 1.1.0
Summary: A simple jinja2-based argument templatizer
Home-page: https://github.com/brian-bk/fyoo
Author: Brian Kleszyk
License: MIT
Project-URL: Documentation, https://fyoo.readthedocs.io
Project-URL: Source, https://github.com/brian-bk/fyoo
Project-URL: Tracker, https://github.com/brian-bk/fyoo/issues
Platform: UNKNOWN
Classifier: Intended Audience :: Developers
Classifier: License :: OSI Approved :: MIT License
Classifier: Programming Language :: Python :: 3.7
Classifier: Programming Language :: Python :: 3.8
Classifier: Programming Language :: Python :: 3.9
Classifier: Programming Language :: Python :: 3.10
Requires-Python: >=3.7
License-File: LICENSE
Requires-Dist: jinja2
Requires-Dist: PyYAML
Requires-Dist: pytz
Provides-Extra: all
Requires-Dist: autopep8 ; extra == 'all'
Requires-Dist: pytest ; extra == 'all'
Requires-Dist: twine ; extra == 'all'
Requires-Dist: sphinx-autobuild ; extra == 'all'
Requires-Dist: codecov ; extra == 'all'
Requires-Dist: coverage ; extra == 'all'
Requires-Dist: pylint ; extra == 'all'
Requires-Dist: pytest-cov ; extra == 'all'
Requires-Dist: sphinx-argparse ; extra == 'all'
Requires-Dist: pytest-env ; extra == 'all'
Requires-Dist: sphinx (>=2.1) ; extra == 'all'
Provides-Extra: dev
Requires-Dist: autopep8 ; extra == 'dev'
Requires-Dist: pytest ; extra == 'dev'
Requires-Dist: twine ; extra == 'dev'
Requires-Dist: sphinx-autobuild ; extra == 'dev'
Requires-Dist: codecov ; extra == 'dev'
Requires-Dist: coverage ; extra == 'dev'
Requires-Dist: pylint ; extra == 'dev'
Requires-Dist: pytest-cov ; extra == 'dev'
Requires-Dist: sphinx-argparse ; extra == 'dev'
Requires-Dist: pytest-env ; extra == 'dev'
Requires-Dist: sphinx (>=2.1) ; extra == 'dev'
Provides-Extra: test
Requires-Dist: pylint ; extra == 'test'
Requires-Dist: pytest ; extra == 'test'
Requires-Dist: pytest-cov ; extra == 'test'
Requires-Dist: pytest-env ; extra == 'test'
